bridger/__init__.py
bridger/admin.py
bridger/auth.py
bridger/buttons/__init__.py
bridger/buttons/bases.py
bridger/buttons/buttons.py
bridger/buttons/enums.py
bridger/buttons/metadata.py
bridger/buttons/metadata_config.py
bridger/buttons/mixins.py
bridger/buttons/viewsets.py
bridger/display/__init__.py
bridger/display/formatting.py
bridger/display/instance_display.py
bridger/display/list_display.py
bridger/display/metadata_config.py
bridger/display.py
bridger/docs/__init__.py
bridger/endpoints/__init__.py
bridger/endpoints/metadata_config.py
bridger/enums.py
bridger/filters/__init__.py
bridger/filters/backends.py
bridger/filters/defaults.py
bridger/filters/fields.py
bridger/filters/filterset.py
bridger/filters/mixins.py
bridger/frontend.py
bridger/frontend_user_configuration.py
bridger/fsm/__init__.py
bridger/fsm/markdown_extensions.py
bridger/fsm/mixins.py
bridger/history/__init__.py
bridger/history/serializers.py
bridger/history/viewsets.py
bridger/management/__init__.py
bridger/management/commands/__init__.py
bridger/management/commands/bootstrap.py
bridger/markdown/__init__.py
bridger/markdown/admin.py
bridger/markdown/models.py
bridger/markdown/template.py
bridger/markdown/views.py
bridger/menus/__init__.py
bridger/menus/menus.py
bridger/menus/registry.py
bridger/menus/views.py
bridger/messages.py
bridger/metadata/__init__.py
bridger/metadata/configs/__init__.py
bridger/metadata/configs/documentation.py
bridger/metadata/configs/fields.py
bridger/metadata/configs/filter_fields.py
bridger/metadata/configs/identifier.py
bridger/metadata/configs/ordering_fields.py
bridger/metadata/configs/pagination.py
bridger/metadata/configs/pk.py
bridger/metadata/configs/search_fields.py
bridger/metadata/configs/type.py
bridger/metadata/metadata.py
bridger/metadata/mixins.py
bridger/metadata/views.py
bridger/migrations/0001_initial.py
bridger/migrations/0002_notification.py
bridger/migrations/0003_auto_20200218_1329.py
bridger/migrations/0004_auto_20200327_1152.py
django_bridger-0.11.32.dist-info/WHEEL
django_bridger-0.11.32.dist-info/METADATA
django_bridger-0.11.32.dist-info/RECORD
