Metadata-Version: 2.1
Name: django-bridger
Version: 0.11.32
Summary: The bridge between a Django Backend and a Javascript based Frontend
Author: Christopher Wittlinger
Author-email: c.wittlinger@intellineers.com
Requires-Python: ==3.9.5
Classifier: Programming Language :: Python :: 3
Requires-Dist: asgiref (>=3.0.0,<4.0.0)
Requires-Dist: celery[redis] (>=5.0.0,<6.0.0)
Requires-Dist: channels (>=3.0.0,<4.0.0)
Requires-Dist: channels_redis[cryptography] (>=3.0.0,<4.0.0)
Requires-Dist: colorlog (>=4.1.0,<4.2.0)
Requires-Dist: daphne (>=3.0.0,<4.0.0)
Requires-Dist: dj-database-url (<1.0.0)
Requires-Dist: django (>=3.0.0,<4.0.0)
Requires-Dist: django-celery-beat (>=2.0.0,<3.0.0)
Requires-Dist: django-cors-headers (>=3.0.0,<4.0.0)
Requires-Dist: django-extensions (>=3.0.0,<4.0.0)
Requires-Dist: django-filter (>=2.0.0,<3.0.0)
Requires-Dist: django-fsm (>=2.0.0,<3.0.0)
Requires-Dist: django-mptt (<1.0.0)
Requires-Dist: django-rest-fuzzysearch (<1.0.0)
Requires-Dist: django-simple-history (>=3.0.0,<4.0.0)
Requires-Dist: django-storages (>=1.0.0,<2.0.0)
Requires-Dist: djangorestframework (>=3.0.0,<4.0.0)
Requires-Dist: djangorestframework-simplejwt (>=4.0.0,<5.0.0)
Requires-Dist: factory-boy (>=2.0.0,<3.0.0)
Requires-Dist: inscriptis (>=1.1,<2.0)
Requires-Dist: jsonschema (>=3.0.0,<4.0.0)
Requires-Dist: jupyter (>=1.0.0,<2.0.0)
Requires-Dist: markdown (>=3.0.0,<4.0.0)
Requires-Dist: markdown-blockdiag (<1.0.0)
Requires-Dist: numpy (>=1.0.0,<2.0.0)
Requires-Dist: pandas
Requires-Dist: pillow
Requires-Dist: plotly (>=5.0.0,<6.0.0)
Requires-Dist: psycopg2-binary (>=2.0.0,<3.0.0)
Requires-Dist: pyjwt (==1.7.1)
Requires-Dist: pytest-selenium (>=1.0.0,<2.0.0)
Requires-Dist: python-decouple (>=3.0.0,<4.0.0)
Requires-Dist: python-slugify
Requires-Dist: requests (>=2.0.0,<3.0.0)
Requires-Dist: safety (>=1.0.0,<2.0.0)
Requires-Dist: selenium (>=3.0.0,<4.0.0)
Requires-Dist: termcolor (>=1.1.0,<2.0.0)
Requires-Dist: toml (<1.0.0)
